openavalancheproject/__init__.py
openavalancheproject/_modidx.py
openavalancheproject/_nbdev.py
openavalancheproject/convert_to_zarr.py
openavalancheproject/oap_stats.py
openavalancheproject/parse_gfs.py
openavalancheproject/prep_ml.py
openavalancheproject/tsai_simple_transforms.py
openavalancheproject/tsai_utilities.py
openavalancheproject-0.0.4.dist-info/LICENSE
openavalancheproject-0.0.4.dist-info/METADATA
openavalancheproject-0.0.4.dist-info/WHEEL
openavalancheproject-0.0.4.dist-info/entry_points.txt
openavalancheproject-0.0.4.dist-info/top_level.txt
openavalancheproject-0.0.4.dist-info/RECORD
