Metadata-Version: 2.1
Name: openavalancheproject
Version: 0.0.4
Summary: Data Pipeline Processing for Open Avalanche Project from global GFS to ML Data
Home-page: https://github.com/scottcha/openavalancheproject/tree/master/
Author: Scott Chamberlin
Author-email: scott@snowymountainworks.com
License: MIT License
Keywords: openavalancheproject
Classifier: Development Status :: 2 - Pre-Alpha
Classifier: Intended Audience :: Developers
Classifier: Natural Language :: English
Classifier: Programming Language :: Python :: 3.10
Classifier: License :: OSI Approved :: MIT License
Requires-Python: >=3.10
License-File: LICENSE
Requires-Dist: xarray
Requires-Dist: matplotlib
Requires-Dist: pandas
Requires-Dist: salem
Requires-Dist: numpy
Requires-Dist: geopandas
Requires-Dist: joblib
Requires-Dist: zarr
Requires-Dist: pyarrow
Requires-Dist: scipy
Requires-Dist: netCDF4
Requires-Dist: descartes
Requires-Dist: dask
Requires-Dist: toolz
Provides-Extra: dev
